fastframe.cp310-win_amd64.pyd
fastframe-1.0.0.dist-info/METADATA
fastframe-1.0.0.dist-info/WHEEL
fastframe-1.0.0.dist-info/top_level.txt
fastframe-1.0.0.dist-info/RECORD
