Metadata-Version: 2.4
Name: fastframe
Version: 1.0.0
Summary: High-performance DataFrame engine
Author: William
Requires-Python: >=3.6
Dynamic: author
Dynamic: requires-python
Dynamic: summary
